cleanfid/__init__.py
cleanfid/clip_features.py
cleanfid/downloads_helper.py
cleanfid/features.py
cleanfid/fid.py
cleanfid/inception_pytorch.py
cleanfid/inception_torchscript.py
cleanfid/leaderboard.py
cleanfid/resize.py
cleanfid/utils.py
cleanfid/wrappers.py
clean_fid-0.1.34.dist-info/LICENSE
clean_fid-0.1.34.dist-info/METADATA
clean_fid-0.1.34.dist-info/WHEEL
clean_fid-0.1.34.dist-info/top_level.txt
clean_fid-0.1.34.dist-info/RECORD
