Metadata-Version: 2.1
Name: clean-fid
Version: 0.1.34
Summary: FID calculation in PyTorch with proper image resizing and quantization steps
Home-page: https://github.com/GaParmar/clean-fid
Author: Gaurav Parmar
Author-email: gparmar@andrew.cmu.edu
License: UNKNOWN
Platform: UNKNOWN
Classifier: Programming Language :: Python :: 3
Classifier: License :: OSI Approved :: BSD License
Classifier: Operating System :: OS Independent
License-File: LICENSE
Requires-Dist: torch
Requires-Dist: torchvision
Requires-Dist: numpy (>=1.14.3)
Requires-Dist: scipy (>=1.0.1)
Requires-Dist: tqdm (>=4.28.1)
Requires-Dist: pillow (>=8.1)
Requires-Dist: requests (==2.25.1)
